[
  {
    "run_id": "kanyanbao-2026-04-16-150906",
    "source_report_id": "43030159",
    "ticker": "SE",
    "name": "Sea",
    "section": "消费",
    "raw_pdf_path": "runtime/raw_reports/2026-04-16/2026-04-16_SE_43030159_raw.pdf",
    "sanitized_pdf_path": "runtime/sanitized_reports/2026-04-16/2026-04-16_SE_43030159_sanitized.pdf",
    "page_count": 17,
    "file_sha256": "5e9ed9a0384b4c12889d575ee71eebcffd4eb83fb1977e829ce99234a0b73da5",
    "watermark_hits": [
      {
        "page": 1,
        "rule_id": "literal",
        "text": "本报告仅供"
      },
      {
        "page": 1,
        "rule_id": "literal",
        "text": "已记录日志请勿传阅"
      },
      {
        "page": 1,
        "rule_id": "literal_search",
        "text": "本报告仅供"
      },
      {
        "page": 1,
        "rule_id": "literal_search",
        "text": "已记录日志请勿传阅"
      },
      {
        "page": 17,
        "rule_id": "literal",
        "text": "本报告仅供"
      },
      {
        "page": 17,
        "rule_id": "literal_search",
        "text": "本报告仅供"
      }
    ],
    "sanitization_status": "completed",
    "ready_for_summary": true,
    "broker": "N/A",
    "upload_at": "2026-04-16T07:52:00+08:00",
    "is_new": true,
    "error": null
  }
]
